{
  "version": "5",
  "dialect": "pg",
  "id": "b5b01392-1bd1-467b-a5ec-d19f2e3fbee9",
  "prevId": "bdfb4013-5564-484b-acda-95821d0b6654",
  "tables": {
    "categories": {
      "name": "categories",
      "schema": "",
      "columns": {
        "id": {
          "name": "id",
          "type": "serial",
          "primaryKey": true,
          "notNull": true
        },
        "category_name": {
          "name": "category_name",
          "type": "varchar(80)",
          "primaryKey": false,
          "notNull": false
        }
      },
      "indexes": {},
      "foreignKeys": {},
      "compositePrimaryKeys": {}
    },
    "members": {
      "name": "members",
      "schema": "",
      "columns": {
        "id": {
          "name": "id",
          "type": "serial",
          "primaryKey": true,
          "notNull": true
        },
        "member_name": {
          "name": "member_name",
          "type": "varchar(80)",
          "primaryKey": false,
          "notNull": false
        }
      },
      "indexes": {},
      "foreignKeys": {},
      "compositePrimaryKeys": {}
    },
    "records": {
      "name": "records",
      "schema": "",
      "columns": {
        "id": {
          "name": "id",
          "type": "serial",
          "primaryKey": true,
          "notNull": true
        },
        "amount": {
          "name": "amount",
          "type": "numeric(15, 4)",
          "primaryKey": false,
          "notNull": false
        },
        "store_id": {
          "name": "store_id",
          "type": "text",
          "primaryKey": false,
          "notNull": false
        },
        "category_id": {
          "name": "category_id",
          "type": "text",
          "primaryKey": false,
          "notNull": false
        },
        "member_id": {
          "name": "member_id",
          "type": "text",
          "primaryKey": false,
          "notNull": false
        },
        "memo": {
          "name": "memo",
          "type": "varchar(80)",
          "primaryKey": false,
          "notNull": false
        },
        "created_at": {
          "name": "created_at",
          "type": "timestamp",
          "primaryKey": false,
          "notNull": false,
          "default": "now()"
        }
      },
      "indexes": {},
      "foreignKeys": {
        "records_store_id_stores_id_fk": {
          "name": "records_store_id_stores_id_fk",
          "tableFrom": "records",
          "tableTo": "stores",
          "columnsFrom": [
            "store_id"
          ],
          "columnsTo": [
            "id"
          ],
          "onDelete": "no action",
          "onUpdate": "no action"
        },
        "records_category_id_categories_id_fk": {
          "name": "records_category_id_categories_id_fk",
          "tableFrom": "records",
          "tableTo": "categories",
          "columnsFrom": [
            "category_id"
          ],
          "columnsTo": [
            "id"
          ],
          "onDelete": "no action",
          "onUpdate": "no action"
        },
        "records_member_id_members_id_fk": {
          "name": "records_member_id_members_id_fk",
          "tableFrom": "records",
          "tableTo": "members",
          "columnsFrom": [
            "member_id"
          ],
          "columnsTo": [
            "id"
          ],
          "onDelete": "no action",
          "onUpdate": "no action"
        }
      },
      "compositePrimaryKeys": {}
    },
    "stores": {
      "name": "stores",
      "schema": "",
      "columns": {
        "id": {
          "name": "id",
          "type": "serial",
          "primaryKey": true,
          "notNull": true
        },
        "store_name": {
          "name": "store_name",
          "type": "varchar(80)",
          "primaryKey": false,
          "notNull": false
        },
        "category_id": {
          "name": "category_id",
          "type": "text",
          "primaryKey": false,
          "notNull": false
        }
      },
      "indexes": {},
      "foreignKeys": {
        "stores_category_id_categories_id_fk": {
          "name": "stores_category_id_categories_id_fk",
          "tableFrom": "stores",
          "tableTo": "categories",
          "columnsFrom": [
            "category_id"
          ],
          "columnsTo": [
            "id"
          ],
          "onDelete": "no action",
          "onUpdate": "no action"
        }
      },
      "compositePrimaryKeys": {}
    }
  },
  "enums": {},
  "schemas": {},
  "_meta": {
    "schemas": {},
    "tables": {},
    "columns": {}
  }
}